chunksum/__init__.py
chunksum/cdc.py
chunksum/chunksize.py
chunksum/chunksum.py
chunksum/cli.py
chunksum/hash.py
chunksum/iter.py
chunksum/mp.py
chunksum/parser.py
chunksum/utils.py
chunksum-0.6.0.dist-info/entry_points.txt
chunksum-0.6.0.dist-info/LICENSE
chunksum-0.6.0.dist-info/WHEEL
chunksum-0.6.0.dist-info/METADATA
chunksum-0.6.0.dist-info/RECORD
